tablemap/__init__.py
tablemap/tablemap.py
test/__init__.py
test/test_core.py
tablemap-0.3.7.dist-info/LICENSE
tablemap-0.3.7.dist-info/METADATA
tablemap-0.3.7.dist-info/WHEEL
tablemap-0.3.7.dist-info/top_level.txt
tablemap-0.3.7.dist-info/RECORD
