Metadata-Version: 2.1
Name: tablemap
Version: 0.3.7
Summary: sql not knowing sql
Home-page: https://github.com/nalssee/tablemap.git
Author: nalssee
Author-email: jinisrolling@gmail.com
License: MIT
License-File: LICENSE
